[
  {
      "name":"Kunal.Goal1",
      "size":2023,
      "imports":[
         "Kunal.Goal2",
         "Santosh.Goal3",
         "Santosh.Goal4",
         "Santosh.Goal5"
      ]
   },
   {
      "name":"Kunal.Goal2",
      "size":16540,
      "imports":[
        "Kunal.Goal6",
        "Kunal.Goal7"
      ]
   },
   {
      "name":"Santosh.Goal3",
      "size":16541,
      "imports":[
        "Kunal.Goal6",
        "Kunal.Goal7"
      ]
   },
   {
      "name":"Santosh.Goal4",
      "size":16542,
      "imports":[
        "Kunal.Goal6",
        "Kunal.Goal7"
      ]
   },
   {
      "name":"Santosh.Goal5",
      "size":16543,
      "imports":[
         "Kunal.Goal6",
         "Kunal.Goal7"
      ]
   },
   {
      "name":"Kunal.Goal6",
      "size":16544,
      "imports":[
         "Kunal.Goal1"
      ]
   },
   {
      "name":"Kunal.Goal7",
      "size":16545,
      "imports":[
      ]
   }
]
